kdb_python/__init__.py
kdb_python/exceptions.py
kdb_python/common/__init__.py
kdb_python/common/config_parser.py
kdb_python/common/constants.py
kdb_python/common/encrypt_decrypt.py
kdb_python/common/mobile_manager.py
kdb_python/common/profiles.py
kdb_python/common/properties.py
kdb_python/common/random_util.py
kdb_python/common/screenshot.py
kdb_python/common/ssh_connection.py
kdb_python/common/utils.py
kdb_python/config/__init__.py
kdb_python/config/settings.py
kdb_python/report/__init__.py
kdb_python/report/report_manager.py
kdb_python/report/test_case_log.py
kdb_python/report/test_step_log.py
kdb_python/scripts/__init__.py
kdb_python/webdriver/__init__.py
kdb_python/webdriver/alert.py
kdb_python/webdriver/common.py
kdb_python/webdriver/cookies.py
kdb_python/webdriver/files.py
kdb_python/webdriver/json_path.py
kdb_python/webdriver/kdb_webdriver.py
kdb_python/webdriver/kdb_webelement.py
kdb_python/webdriver/keys.py
kdb_python/webdriver/mobile_gestures.py
kdb_python/webdriver/random.py
kdb_python/webdriver/requests.py
kdb_python/webdriver/video.py
kdb_python/webdriver/videoelement.py
kdb_python/webdriver/webdriver_generator.py
kdb_python/webdriver/windows.py
kdb_python/webdriver/actions/__init__.py
kdb_python/webdriver/actions/alert.py
kdb_python/webdriver/actions/cookies.py
kdb_python/webdriver/actions/mobile_gestures.py
kdb_python/webdriver/actions/video.py
kdb_python-1.0.10.dist-info/licenses/LICENSE
kdb_python-1.0.10.dist-info/METADATA
kdb_python-1.0.10.dist-info/WHEEL
kdb_python-1.0.10.dist-info/top_level.txt
kdb_python-1.0.10.dist-info/RECORD
