Metadata-Version: 2.4
Name: kdb-python
Version: 1.0.10
Summary: Automation testing
Author-email: Trucnt <trucnt88@gmail.com>
License-Expression: MIT AND (Apache-2.0 OR BSD-2-Clause)
Project-URL: Homepage, https://github.com/Trucnt/kdb-python-examples
Classifier: Programming Language :: Python :: 3
Classifier: Operating System :: OS Independent
Requires-Python: >=3.10
License-File: LICENSE
Dynamic: license-file
